MANIFEST.in
README.md
setup.py
tarpit/__init__.py
tarpit/checker.py
tarpit/command.py
tarpit/config.py
tarpit/dao.py
tarpit/err.py
tarpit/sa.py
tarpit/task.py
tarpit/test.py
tarpit/toolkit.py
tarpit/web.py
tarpit.egg-info/PKG-INFO
tarpit.egg-info/SOURCES.txt
tarpit.egg-info/dependency_links.txt
tarpit.egg-info/entry_points.txt
tarpit.egg-info/requires.txt
tarpit.egg-info/top_level.txt
tarpit/templates/alembic.ini
tarpit/templates/worker.py
tarpit/templates/alembic/README
tarpit/templates/alembic/env.py
tarpit/templates/alembic/script.py.mako
tarpit/templates/alembic/versions/20190415-1950-init.py
tarpit/templates/controllers/__init__.py
tarpit/templates/controllers/index.py
tarpit/templates/controllers/user.py
tarpit/templates/database/__init__.py
tarpit/templates/database/sqlalchemy_models.py
tarpit/templates/lib/readme.txt
tarpit/templates/mappers/__init__.py
tarpit/templates/mappers/user.py
tarpit/templates/services/__init__.py
tarpit/templates/services/user.py
tarpit/templates/settings/config.yml
tarpit/templates/settings/status.yml
tarpit/templates/storage/__init__.py
tarpit/templates/storage/storage.py
tarpit/templates/test/env.yml
tarpit/templates/test/requests.yml
tarpit/utils/__init__.py
tarpit/utils/arguments.py
tarpit/utils/json_encoder.py
tarpit/utils/logger.py
tarpit/utils/passwd.py
tarpit/utils/regex.py
tarpit/utils/totp.py