Metadata-Version: 1.0
Name: tarpit
Version: 0.0.20
Summary: 一个快速构建服务后台的库，可以快速创建简单后台。
Home-page: https://lazor.cn
Author: plank
Author-email: sieglive@gmail.com
License: GPLv3+
Platform: UNKNOWN
